[{"id":1,"entry_id":6,"framework_id":1,"connected_entry_id":2},{"id":2,"entry_id":2,"framework_id":1,"connected_entry_id":6},{"id":3,"entry_id":20,"framework_id":1,"connected_entry_id":7},{"id":4,"entry_id":7,"framework_id":1,"connected_entry_id":20},{"id":5,"entry_id":31,"framework_id":2,"connected_entry_id":3},{"id":6,"entry_id":3,"framework_id":2,"connected_entry_id":31},{"id":7,"entry_id":3,"framework_id":2,"connected_entry_id":4},{"id":8,"entry_id":4,"framework_id":2,"connected_entry_id":3},{"id":9,"entry_id":4,"framework_id":2,"connected_entry_id":8},{"id":10,"entry_id":8,"framework_id":2,"connected_entry_id":4},{"id":11,"entry_id":35,"framework_id":2,"connected_entry_id":15},{"id":12,"entry_id":15,"framework_id":2,"connected_entry_id":35},{"id":13,"entry_id":38,"framework_id":2,"connected_entry_id":24},{"id":14,"entry_id":24,"framework_id":2,"connected_entry_id":38},{"id":15,"entry_id":39,"framework_id":3,"connected_entry_id":17},{"id":16,"entry_id":17,"framework_id":3,"connected_entry_id":39},{"id":17,"entry_id":40,"framework_id":3,"connected_entry_id":16},{"id":18,"entry_id":16,"framework_id":3,"connected_entry_id":40},{"id":19,"entry_id":43,"framework_id":4,"connected_entry_id":24},{"id":20,"entry_id":24,"framework_id":4,"connected_entry_id":43},{"id":21,"entry_id":52,"framework_id":4,"connected_entry_id":38},{"id":22,"entry_id":38,"framework_id":4,"connected_entry_id":52},{"id":23,"entry_id":38,"framework_id":4,"connected_entry_id":37},{"id":24,"entry_id":37,"framework_id":4,"connected_entry_id":38},{"id":25,"entry_id":37,"framework_id":4,"connected_entry_id":36},{"id":26,"entry_id":36,"framework_id":4,"connected_entry_id":37},{"id":27,"entry_id":36,"framework_id":4,"connected_entry_id":15},{"id":28,"entry_id":15,"framework_id":4,"connected_entry_id":36},{"id":29,"entry_id":64,"framework_id":5,"connected_entry_id":11},{"id":30,"entry_id":11,"framework_id":5,"connected_entry_id":64},{"id":31,"entry_id":59,"framework_id":6,"connected_entry_id":60},{"id":32,"entry_id":60,"framework_id":6,"connected_entry_id":59},{"id":33,"entry_id":60,"framework_id":6,"connected_entry_id":61},{"id":34,"entry_id":61,"framework_id":6,"connected_entry_id":60},{"id":35,"entry_id":78,"framework_id":7,"connected_entry_id":15},{"id":36,"entry_id":15,"framework_id":7,"connected_entry_id":78},{"id":37,"entry_id":80,"framework_id":7,"connected_entry_id":52},{"id":38,"entry_id":52,"framework_id":7,"connected_entry_id":80},{"id":39,"entry_id":82,"framework_id":8,"connected_entry_id":8},{"id":40,"entry_id":8,"framework_id":8,"connected_entry_id":82},{"id":41,"entry_id":89,"framework_id":9,"connected_entry_id":81},{"id":42,"entry_id":81,"framework_id":9,"connected_entry_id":89},{"id":43,"entry_id":90,"framework_id":10,"connected_entry_id":59},{"id":44,"entry_id":59,"framework_id":10,"connected_entry_id":90},{"id":45,"entry_id":100,"framework_id":11,"connected_entry_id":89},{"id":46,"entry_id":89,"framework_id":11,"connected_entry_id":100},{"id":47,"entry_id":102,"framework_id":11,"connected_entry_id":92},{"id":48,"entry_id":92,"framework_id":11,"connected_entry_id":102},{"id":49,"entry_id":102,"framework_id":11,"connected_entry_id":8},{"id":50,"entry_id":8,"framework_id":11,"connected_entry_id":102},{"id":51,"entry_id":92,"framework_id":11,"connected_entry_id":63},{"id":52,"entry_id":63,"framework_id":11,"connected_entry_id":92},{"id":53,"entry_id":92,"framework_id":11,"connected_entry_id":8},{"id":54,"entry_id":8,"framework_id":11,"connected_entry_id":92},{"id":55,"entry_id":103,"framework_id":11,"connected_entry_id":62},{"id":56,"entry_id":62,"framework_id":11,"connected_entry_id":103},{"id":57,"entry_id":8,"framework_id":11,"connected_entry_id":7},{"id":58,"entry_id":7,"framework_id":11,"connected_entry_id":8},{"id":59,"entry_id":106,"framework_id":11,"connected_entry_id":13},{"id":60,"entry_id":13,"framework_id":11,"connected_entry_id":106},{"id":61,"entry_id":108,"framework_id":11,"connected_entry_id":23},{"id":62,"entry_id":23,"framework_id":11,"connected_entry_id":108},{"id":63,"entry_id":23,"framework_id":11,"connected_entry_id":24},{"id":64,"entry_id":24,"framework_id":11,"connected_entry_id":23},{"id":65,"entry_id":117,"framework_id":12,"connected_entry_id":90},{"id":66,"entry_id":90,"framework_id":12,"connected_entry_id":117},{"id":67,"entry_id":125,"framework_id":12,"connected_entry_id":71},{"id":68,"entry_id":71,"framework_id":12,"connected_entry_id":125},{"id":69,"entry_id":71,"framework_id":12,"connected_entry_id":75},{"id":70,"entry_id":75,"framework_id":12,"connected_entry_id":71},{"id":71,"entry_id":75,"framework_id":12,"connected_entry_id":123},{"id":72,"entry_id":123,"framework_id":12,"connected_entry_id":75},{"id":73,"entry_id":75,"framework_id":12,"connected_entry_id":124},{"id":74,"entry_id":124,"framework_id":12,"connected_entry_id":75},{"id":75,"entry_id":135,"framework_id":13,"connected_entry_id":93},{"id":76,"entry_id":93,"framework_id":13,"connected_entry_id":135},{"id":77,"entry_id":93,"framework_id":13,"connected_entry_id":94},{"id":78,"entry_id":94,"framework_id":13,"connected_entry_id":93},{"id":79,"entry_id":146,"framework_id":13,"connected_entry_id":97},{"id":80,"entry_id":97,"framework_id":13,"connected_entry_id":146},{"id":81,"entry_id":97,"framework_id":13,"connected_entry_id":98},{"id":82,"entry_id":98,"framework_id":13,"connected_entry_id":97},{"id":83,"entry_id":98,"framework_id":13,"connected_entry_id":99},{"id":84,"entry_id":99,"framework_id":13,"connected_entry_id":98},{"id":85,"entry_id":99,"framework_id":13,"connected_entry_id":100},{"id":86,"entry_id":100,"framework_id":13,"connected_entry_id":99},{"id":87,"entry_id":100,"framework_id":13,"connected_entry_id":89},{"id":88,"entry_id":89,"framework_id":13,"connected_entry_id":100},{"id":89,"entry_id":89,"framework_id":13,"connected_entry_id":101},{"id":90,"entry_id":101,"framework_id":13,"connected_entry_id":89},{"id":91,"entry_id":152,"framework_id":14,"connected_entry_id":27},{"id":92,"entry_id":27,"framework_id":14,"connected_entry_id":152},{"id":93,"entry_id":164,"framework_id":15,"connected_entry_id":2},{"id":94,"entry_id":2,"framework_id":15,"connected_entry_id":164},{"id":95,"entry_id":2,"framework_id":15,"connected_entry_id":3},{"id":96,"entry_id":3,"framework_id":15,"connected_entry_id":2},{"id":97,"entry_id":3,"framework_id":15,"connected_entry_id":4},{"id":98,"entry_id":4,"framework_id":15,"connected_entry_id":3},{"id":99,"entry_id":4,"framework_id":15,"connected_entry_id":8},{"id":100,"entry_id":8,"framework_id":15,"connected_entry_id":4},{"id":101,"entry_id":165,"framework_id":16,"connected_entry_id":153},{"id":102,"entry_id":153,"framework_id":16,"connected_entry_id":165},{"id":103,"entry_id":153,"framework_id":16,"connected_entry_id":154},{"id":104,"entry_id":154,"framework_id":16,"connected_entry_id":153},{"id":105,"entry_id":154,"framework_id":16,"connected_entry_id":155},{"id":106,"entry_id":155,"framework_id":16,"connected_entry_id":154},{"id":107,"entry_id":155,"framework_id":16,"connected_entry_id":156},{"id":108,"entry_id":156,"framework_id":16,"connected_entry_id":155},{"id":109,"entry_id":156,"framework_id":16,"connected_entry_id":157},{"id":110,"entry_id":157,"framework_id":16,"connected_entry_id":156},{"id":111,"entry_id":157,"framework_id":16,"connected_entry_id":158},{"id":112,"entry_id":158,"framework_id":16,"connected_entry_id":157},{"id":113,"entry_id":158,"framework_id":16,"connected_entry_id":159},{"id":114,"entry_id":159,"framework_id":16,"connected_entry_id":158},{"id":115,"entry_id":159,"framework_id":16,"connected_entry_id":155},{"id":116,"entry_id":155,"framework_id":16,"connected_entry_id":159},{"id":117,"entry_id":171,"framework_id":18,"connected_entry_id":170},{"id":118,"entry_id":170,"framework_id":18,"connected_entry_id":171},{"id":119,"entry_id":182,"framework_id":18,"connected_entry_id":53},{"id":120,"entry_id":53,"framework_id":18,"connected_entry_id":182},{"id":121,"entry_id":53,"framework_id":18,"connected_entry_id":52},{"id":122,"entry_id":52,"framework_id":18,"connected_entry_id":53},{"id":123,"entry_id":52,"framework_id":18,"connected_entry_id":38},{"id":124,"entry_id":38,"framework_id":18,"connected_entry_id":52},{"id":125,"entry_id":38,"framework_id":18,"connected_entry_id":23},{"id":126,"entry_id":23,"framework_id":18,"connected_entry_id":38},{"id":127,"entry_id":185,"framework_id":18,"connected_entry_id":19},{"id":128,"entry_id":19,"framework_id":18,"connected_entry_id":185},{"id":129,"entry_id":191,"framework_id":19,"connected_entry_id":187},{"id":130,"entry_id":187,"framework_id":19,"connected_entry_id":191},{"id":131,"entry_id":204,"framework_id":21,"connected_entry_id":115},{"id":132,"entry_id":115,"framework_id":21,"connected_entry_id":204},{"id":133,"entry_id":210,"framework_id":21,"connected_entry_id":8},{"id":134,"entry_id":8,"framework_id":21,"connected_entry_id":210},{"id":135,"entry_id":217,"framework_id":21,"connected_entry_id":204},{"id":136,"entry_id":204,"framework_id":21,"connected_entry_id":217},{"id":137,"entry_id":231,"framework_id":22,"connected_entry_id":88},{"id":138,"entry_id":88,"framework_id":22,"connected_entry_id":231},{"id":139,"entry_id":88,"framework_id":22,"connected_entry_id":89},{"id":140,"entry_id":89,"framework_id":22,"connected_entry_id":88},{"id":141,"entry_id":89,"framework_id":22,"connected_entry_id":81},{"id":142,"entry_id":81,"framework_id":22,"connected_entry_id":89},{"id":143,"entry_id":81,"framework_id":22,"connected_entry_id":82},{"id":144,"entry_id":82,"framework_id":22,"connected_entry_id":81},{"id":145,"entry_id":82,"framework_id":22,"connected_entry_id":8},{"id":146,"entry_id":8,"framework_id":22,"connected_entry_id":82},{"id":147,"entry_id":8,"framework_id":22,"connected_entry_id":9},{"id":148,"entry_id":9,"framework_id":22,"connected_entry_id":8},{"id":149,"entry_id":8,"framework_id":22,"connected_entry_id":7},{"id":150,"entry_id":7,"framework_id":22,"connected_entry_id":8},{"id":151,"entry_id":9,"framework_id":22,"connected_entry_id":10},{"id":152,"entry_id":10,"framework_id":22,"connected_entry_id":9},{"id":153,"entry_id":10,"framework_id":22,"connected_entry_id":11},{"id":154,"entry_id":11,"framework_id":22,"connected_entry_id":10},{"id":155,"entry_id":11,"framework_id":22,"connected_entry_id":12},{"id":156,"entry_id":12,"framework_id":22,"connected_entry_id":11},{"id":157,"entry_id":12,"framework_id":22,"connected_entry_id":13},{"id":158,"entry_id":13,"framework_id":22,"connected_entry_id":12},{"id":159,"entry_id":13,"framework_id":22,"connected_entry_id":14},{"id":160,"entry_id":14,"framework_id":22,"connected_entry_id":13},{"id":161,"entry_id":14,"framework_id":22,"connected_entry_id":15},{"id":162,"entry_id":15,"framework_id":22,"connected_entry_id":14},{"id":163,"entry_id":14,"framework_id":22,"connected_entry_id":21},{"id":164,"entry_id":21,"framework_id":22,"connected_entry_id":14},{"id":165,"entry_id":15,"framework_id":22,"connected_entry_id":16},{"id":166,"entry_id":16,"framework_id":22,"connected_entry_id":15},{"id":167,"entry_id":16,"framework_id":22,"connected_entry_id":17},{"id":168,"entry_id":17,"framework_id":22,"connected_entry_id":16},{"id":169,"entry_id":17,"framework_id":22,"connected_entry_id":18},{"id":170,"entry_id":18,"framework_id":22,"connected_entry_id":17},{"id":171,"entry_id":18,"framework_id":22,"connected_entry_id":19},{"id":172,"entry_id":19,"framework_id":22,"connected_entry_id":18},{"id":173,"entry_id":22,"framework_id":22,"connected_entry_id":23},{"id":174,"entry_id":23,"framework_id":22,"connected_entry_id":22},{"id":175,"entry_id":23,"framework_id":22,"connected_entry_id":24},{"id":176,"entry_id":24,"framework_id":22,"connected_entry_id":23},{"id":177,"entry_id":245,"framework_id":23,"connected_entry_id":102},{"id":178,"entry_id":102,"framework_id":23,"connected_entry_id":245}]